Metadata-Version: 2.1
Name: ginkgopy
Version: 0.0.2
Summary: PyPI Tutorial
Home-page: https://xxx.com/
Author: dong'zu'an
Author-email: albert_dza@foxmail.com
License: UNKNOWN
Platform: UNKNOWN
Classifier: Programming Language :: Python :: 3
Classifier: License :: OSI Approved :: MIT License
Classifier: Operating System :: OS Independent
